LICENSE
MANIFEST.in
README.rst
setup.cfg
setup.py
djupiter/__init__.py
djupiter/admin.py
djupiter/apps.py
djupiter/factories.py
djupiter/managers.py
djupiter/models.py
djupiter/permissions.py
djupiter/serializers.py
djupiter/tests.py
djupiter/urls.py
djupiter/views.py
djupiter.egg-info/PKG-INFO
djupiter.egg-info/SOURCES.txt
djupiter.egg-info/dependency_links.txt
djupiter.egg-info/requires.txt
djupiter.egg-info/top_level.txt
djupiter/migrations/0001_initial.py
djupiter/migrations/0002_superadmin.py
djupiter/migrations/0003_passwordresetcode.py
djupiter/migrations/0004_auto_20210125_2042.py
djupiter/migrations/0005_auto_20210201_2047.py
djupiter/migrations/0006_auto_20210201_2123.py
djupiter/migrations/0007_auto_20210203_2258.py
djupiter/migrations/0008_commoner.py
djupiter/migrations/0009_auto_20210302_1540.py
djupiter/migrations/__init__.py
djupiter/templates/djupiter/email/confirmation.html
djupiter/templates/djupiter/email/password-reset-code.html
docs/.gitkeep
docs/index.md
docs/FAQ/faq.md
docs/models/models.md
docs/models/serializers.md
docs/views/custom-views.md
docs/views/index.md